deploy_quack/__init__.py
deploy_quack/cli.py
deploy_quack-0.1.0.dist-info/METADATA
deploy_quack-0.1.0.dist-info/WHEEL
deploy_quack-0.1.0.dist-info/entry_points.txt
deploy_quack-0.1.0.dist-info/top_level.txt
deploy_quack-0.1.0.dist-info/RECORD
