Metadata-Version: 2.4
Name: deploy-quack
Version: 0.1.0
Summary: An awesome tool to deploy applications with docker swarm -- COMING SOON
Requires-Python: >=3.13
